inspire_eu/__init__.py
inspire_eu/apps.py
inspire_eu/urls.py
inspire_eu/utils.py
inspire_eu/views.py
inspire_eu/admin/__init__.py
inspire_eu/management/__init__.py
inspire_eu/management/commands/__init__.py
inspire_eu/management/commands/load_initial_inspire.py
inspire_eu/migrations/0001_initial.py
inspire_eu/migrations/0002_inspire_eu_core.py
inspire_eu/migrations/0003_typo_fixed_added_baseinspireeumodel.py
inspire_eu/migrations/0004_auto_20240703.py
inspire_eu/migrations/__init__.py
inspire_eu/models/__init__.py
inspire_eu/models/abstract.py
inspire_eu/models/core.py
inspire_eu/models/buildings/__init__.py
inspire_eu/models/buildings/abstract.py
inspire_eu/models/buildings/admin.py
inspire_eu/models/cadastral_parcels/__init__.py
inspire_eu/models/cadastral_parcels/abstract.py
inspire_eu/models/cadastral_parcels/admin.py
inspire_eu/static/css/inspire_eu.css
inspire_eu/static/js/inspire_eu.js
inspire_eu/templates/inspire_eu/base.html
inspire_eu/test_utils/__init__.py
inspire_eu/test_utils/test_app/__init__.py
inspire_eu/test_utils/test_app/admin.py
inspire_eu/test_utils/test_app/apps.py
inspire_eu/test_utils/test_app/models.py
inspire_eu/test_utils/test_app/migrations/__init__.py
django_inspire_eu-0.2.4.dist-info/AUTHORS.rst
django_inspire_eu-0.2.4.dist-info/LICENSE
django_inspire_eu-0.2.4.dist-info/METADATA
django_inspire_eu-0.2.4.dist-info/WHEEL
django_inspire_eu-0.2.4.dist-info/top_level.txt
django_inspire_eu-0.2.4.dist-info/RECORD
