Metadata-Version: 2.1
Name: django-inspire-eu
Version: 0.2.4
Summary: Django implementation from the the themes of infrastructure for spatial information in Europe (INSPIRE)
Home-page: https://github.com/xusy2k/django-inspire-eu
Author: Jesús Zoyo
Author-email: xus@zoyolabs.com
License: MIT
Keywords: django-inspire-eu,django,gis,gdal
Classifier: Development Status :: 4 - Beta
Classifier: Framework :: Django :: 2.0
Classifier: Framework :: Django :: 2.1
Classifier: Framework :: Django :: 2.2
Classifier: Framework :: Django :: 3.0
Classifier: Framework :: Django :: 3.1
Classifier: Framework :: Django :: 4.0
Classifier: Framework :: Django :: 4.1
Classifier: Framework :: Django :: 4.2
Classifier: Framework :: Django :: 5.1
Classifier: Intended Audience :: Developers
Classifier: License :: OSI Approved :: BSD License
Classifier: Natural Language :: English
Classifier: Programming Language :: Python :: 3.6
Classifier: Programming Language :: Python :: 3.7
Classifier: Programming Language :: Python :: 3.8
Classifier: Programming Language :: Python :: 3.9
Classifier: Programming Language :: Python :: 3.10
Classifier: Programming Language :: Python :: 3.11
Classifier: Programming Language :: Python :: 3.12
License-File: LICENSE
License-File: AUTHORS.rst
